{
  "config": "{\"version\":\"5.57\",\"themeCollection\":{\"baseTheme\":{\"name\":\"CY24SU08\",\"version\":\"5.57\",\"type\":2}},\"activeSectionIndex\":0,\"defaultDrillFilterOtherVisuals\":true,\"slowDataSourceSettings\":{\"isCrossHighlightingDisabled\":false,\"isSlicerSelectionsButtonEnabled\":false,\"isFilterSelectionsButtonEnabled\":false,\"isFieldWellButtonEnabled\":false,\"isApplyAllButtonEnabled\":false},\"linguisticSchemaSyncVersion\":2,\"settings\":{\"useNewFilterPaneExperience\":true,\"allowChangeFilterTypes\":true,\"useStylableVisualContainerHeader\":true,\"queryLimitOption\":6,\"exportDataMode\":1,\"useDefaultAggregateDisplayName\":true,\"useEnhancedTooltips\":true},\"objects\":{\"section\":[{\"properties\":{\"verticalAlignment\":{\"expr\":{\"Literal\":{\"Value\":\"'Top'\"}}}}}]}}",
  "layoutOptimization": 0,
  "resourcePackages": [
    {
      "resourcePackage": {
        "disabled": false,
        "items": [
          {
            "name": "background07180881768150638.svg",
            "path": "background07180881768150638.svg",
            "type": 100
          }
        ],
        "name": "RegisteredResources",
        "type": 1
      }
    },
    {
      "resourcePackage": {
        "disabled": false,
        "items": [
          {
            "name": "CY24SU08",
            "path": "BaseThemes/CY24SU08.json",
            "type": 202
          }
        ],
        "name": "SharedResources",
        "type": 2
      }
    }
  ],
  "sections": [
    {
      "config": "{\"relationships\":[{\"source\":\"2a2de02001e1ddaa717a\",\"target\":\"b81a67c032db77c39c72\",\"type\":3}],\"objects\":{\"background\":[{\"properties\":{\"image\":{\"image\":{\"name\":{\"expr\":{\"Literal\":{\"Value\":\"'background.svg'\"}}},\"url\":{\"expr\":{\"ResourcePackageItem\":{\"PackageName\":\"RegisteredResources\",\"PackageType\":1,\"ItemName\":\"background07180881768150638.svg\"}}},\"scaling\":{\"expr\":{\"Literal\":{\"Value\":\"'Normal'\"}}}}},\"transparency\":{\"expr\":{\"Literal\":{\"Value\":\"0D\"}}}}}]}}",
      "displayName": "Página 1",
      "displayOption": 1,
      "filters": "[]",
      "height": 720.00,
      "name": "0cecd120b0213e085a56",
      "visualContainers": [
        {
          "config": "{\"name\":\"2a2de02001e1ddaa717a\",\"layouts\":[{\"id\":0,\"position\":{\"x\":981,\"y\":23,\"z\":1000,\"width\":273,\"height\":98,\"tabOrder\":1000}}],\"singleVisual\":{\"visualType\":\"slicer\",\"projections\":{\"Values\":[{\"queryRef\":\"Ações.Date\",\"active\":true}]},\"prototypeQuery\":{\"Version\":2,\"From\":[{\"Name\":\"a\",\"Entity\":\"Ações\",\"Type\":0}],\"Select\":[{\"Column\":{\"Expression\":{\"SourceRef\":{\"Source\":\"a\"}},\"Property\":\"Date\"},\"Name\":\"Ações.Date\",\"NativeReferenceName\":\"Date\"}],\"OrderBy\":[{\"Direction\":1,\"Expression\":{\"Column\":{\"Expression\":{\"SourceRef\":{\"Source\":\"a\"}},\"Property\":\"Date\"}}}]},\"drillFilterOtherVisuals\":true,\"hasDefaultSort\":true,\"objects\":{\"data\":[{\"properties\":{\"startDate\":{\"expr\":{\"Literal\":{\"Value\":\"datetime'2023-08-31T00:00:00'\"}}},\"endDate\":{\"expr\":{\"Literal\":{\"Value\":\"datetime'2024-08-30T00:00:00'\"}}},\"mode\":{\"expr\":{\"Literal\":{\"Value\":\"'Between'\"}}}}}],\"date\":[{\"properties\":{\"fontColor\":{\"solid\":{\"color\":{\"expr\":{\"ThemeDataColor\":{\"ColorId\":0,\"Percent\":0}}}}}}}],\"header\":[{\"properties\":{\"show\":{\"expr\":{\"Literal\":{\"Value\":\"false\"}}}}}],\"general\":[{\"properties\":{\"filter\":{\"filter\":{\"Version\":2,\"From\":[{\"Name\":\"a\",\"Entity\":\"Ações\",\"Type\":0}],\"Where\":[{\"Condition\":{\"And\":{\"Left\":{\"Comparison\":{\"ComparisonKind\":2,\"Left\":{\"Column\":{\"Expression\":{\"SourceRef\":{\"Source\":\"a\"}},\"Property\":\"Date\"}},\"Right\":{\"Literal\":{\"Value\":\"datetime'2023-08-31T00:00:00'\"}}}},\"Right\":{\"Comparison\":{\"ComparisonKind\":3,\"Left\":{\"Column\":{\"Expression\":{\"SourceRef\":{\"Source\":\"a\"}},\"Property\":\"Date\"}},\"Right\":{\"Literal\":{\"Value\":\"datetime'2024-08-31T00:00:00'\"}}}}}}}]}}}}]},\"vcObjects\":{\"background\":[{\"properties\":{\"show\":{\"expr\":{\"Literal\":{\"Value\":\"false\"}}}}}]}}}",
          "filters": "[]",
          "height": 98.00,
          "width": 273.00,
          "x": 981.00,
          "y": 23.00,
          "z": 1000.00
        },
        {
          "config": "{\"name\":\"82be5e7cee143b9a944e\",\"layouts\":[{\"id\":0,\"position\":{\"x\":0,\"y\":321,\"z\":3000,\"width\":239,\"height\":150,\"tabOrder\":3000}}],\"singleVisual\":{\"visualType\":\"card\",\"projections\":{\"Values\":[{\"queryRef\":\"Sum(Ações.Close)\"}]},\"prototypeQuery\":{\"Version\":2,\"From\":[{\"Name\":\"a\",\"Entity\":\"Ações\",\"Type\":0}],\"Select\":[{\"Aggregation\":{\"Expression\":{\"Column\":{\"Expression\":{\"SourceRef\":{\"Source\":\"a\"}},\"Property\":\"Close\"}},\"Function\":3},\"Name\":\"Sum(Ações.Close)\",\"NativeReferenceName\":\"Mínimo de Close\"}],\"OrderBy\":[{\"Direction\":2,\"Expression\":{\"Aggregation\":{\"Expression\":{\"Column\":{\"Expression\":{\"SourceRef\":{\"Source\":\"a\"}},\"Property\":\"Close\"}},\"Function\":3}}}]},\"drillFilterOtherVisuals\":true,\"hasDefaultSort\":true,\"objects\":{\"labels\":[{\"properties\":{\"fontSize\":{\"expr\":{\"Literal\":{\"Value\":\"20D\"}}},\"color\":{\"solid\":{\"color\":{\"expr\":{\"ThemeDataColor\":{\"ColorId\":0,\"Percent\":0}}}}},\"labelDisplayUnits\":{\"expr\":{\"Literal\":{\"Value\":\"1D\"}}}}}],\"categoryLabels\":[{\"properties\":{\"show\":{\"expr\":{\"Literal\":{\"Value\":\"false\"}}}}}]},\"vcObjects\":{\"title\":[{\"properties\":{\"titleWrap\":{\"expr\":{\"Literal\":{\"Value\":\"true\"}}}}}],\"background\":[{\"properties\":{\"show\":{\"expr\":{\"Literal\":{\"Value\":\"false\"}}},\"transparency\":{\"expr\":{\"Literal\":{\"Value\":\"0D\"}}}}}],\"border\":[{\"properties\":{\"width\":{\"expr\":{\"Literal\":{\"Value\":\"1D\"}}}}}]}}}",
          "filters": "[]",
          "height": 150.00,
          "width": 239.00,
          "x": 0.00,
          "y": 321.00,
          "z": 3000.00
        },
        {
          "config": "{\"name\":\"91d52dd30d08bd68b649\",\"layouts\":[{\"id\":0,\"position\":{\"x\":0,\"y\":434,\"z\":4000,\"width\":239,\"height\":150,\"tabOrder\":4000}}],\"singleVisual\":{\"visualType\":\"card\",\"projections\":{\"Values\":[{\"queryRef\":\"Sum(Ações.Close)\"}]},\"prototypeQuery\":{\"Version\":2,\"From\":[{\"Name\":\"a\",\"Entity\":\"Ações\",\"Type\":0}],\"Select\":[{\"Aggregation\":{\"Expression\":{\"Column\":{\"Expression\":{\"SourceRef\":{\"Source\":\"a\"}},\"Property\":\"Close\"}},\"Function\":4},\"Name\":\"Sum(Ações.Close)\",\"NativeReferenceName\":\"Máximo de Close\"}],\"OrderBy\":[{\"Direction\":2,\"Expression\":{\"Aggregation\":{\"Expression\":{\"Column\":{\"Expression\":{\"SourceRef\":{\"Source\":\"a\"}},\"Property\":\"Close\"}},\"Function\":4}}}]},\"drillFilterOtherVisuals\":true,\"hasDefaultSort\":true,\"objects\":{\"labels\":[{\"properties\":{\"fontSize\":{\"expr\":{\"Literal\":{\"Value\":\"20D\"}}},\"color\":{\"solid\":{\"color\":{\"expr\":{\"ThemeDataColor\":{\"ColorId\":0,\"Percent\":0}}}}},\"labelDisplayUnits\":{\"expr\":{\"Literal\":{\"Value\":\"1D\"}}}}}],\"categoryLabels\":[{\"properties\":{\"show\":{\"expr\":{\"Literal\":{\"Value\":\"false\"}}}}}]},\"vcObjects\":{\"title\":[{\"properties\":{\"titleWrap\":{\"expr\":{\"Literal\":{\"Value\":\"true\"}}}}}],\"background\":[{\"properties\":{\"show\":{\"expr\":{\"Literal\":{\"Value\":\"false\"}}},\"transparency\":{\"expr\":{\"Literal\":{\"Value\":\"0D\"}}}}}],\"border\":[{\"properties\":{\"width\":{\"expr\":{\"Literal\":{\"Value\":\"1D\"}}}}}]}}}",
          "filters": "[]",
          "height": 150.00,
          "width": 239.00,
          "x": 0.00,
          "y": 434.00,
          "z": 4000.00
        },
        {
          "config": "{\"name\":\"b81a67c032db77c39c72\",\"layouts\":[{\"id\":0,\"position\":{\"x\":0,\"y\":232,\"z\":2000,\"width\":239,\"height\":103,\"tabOrder\":2000}}],\"singleVisual\":{\"visualType\":\"card\",\"projections\":{\"Values\":[{\"queryRef\":\"Sum(Ações.Close)\"}]},\"prototypeQuery\":{\"Version\":2,\"From\":[{\"Name\":\"a\",\"Entity\":\"Ações\",\"Type\":0}],\"Select\":[{\"Aggregation\":{\"Expression\":{\"Column\":{\"Expression\":{\"SourceRef\":{\"Source\":\"a\"}},\"Property\":\"Close\"}},\"Function\":0},\"Name\":\"Sum(Ações.Close)\",\"NativeReferenceName\":\"Soma de Close\"}],\"OrderBy\":[{\"Direction\":2,\"Expression\":{\"Aggregation\":{\"Expression\":{\"Column\":{\"Expression\":{\"SourceRef\":{\"Source\":\"a\"}},\"Property\":\"Close\"}},\"Function\":0}}}]},\"drillFilterOtherVisuals\":true,\"hasDefaultSort\":true,\"objects\":{\"categoryLabels\":[{\"properties\":{\"show\":{\"expr\":{\"Literal\":{\"Value\":\"false\"}}}}}],\"labels\":[{\"properties\":{\"color\":{\"solid\":{\"color\":{\"expr\":{\"ThemeDataColor\":{\"ColorId\":0,\"Percent\":0}}}}},\"labelDisplayUnits\":{\"expr\":{\"Literal\":{\"Value\":\"1D\"}}},\"fontSize\":{\"expr\":{\"Literal\":{\"Value\":\"20D\"}}}}}]},\"vcObjects\":{\"background\":[{\"properties\":{\"show\":{\"expr\":{\"Literal\":{\"Value\":\"false\"}}}}}]}}}",
          "filters": "[{\"name\":\"7c6176a6e5a783367976\",\"expression\":{\"Column\":{\"Expression\":{\"SourceRef\":{\"Entity\":\"Ações\"}},\"Property\":\"Date\"}},\"filter\":{\"Version\":2,\"From\":[{\"Name\":\"subquery\",\"Expression\":{\"Subquery\":{\"Query\":{\"Version\":2,\"From\":[{\"Name\":\"a\",\"Entity\":\"Ações\",\"Type\":0}],\"Select\":[{\"Column\":{\"Expression\":{\"SourceRef\":{\"Source\":\"a\"}},\"Property\":\"Date\"},\"Name\":\"field\"}],\"OrderBy\":[{\"Direction\":2,\"Expression\":{\"Aggregation\":{\"Expression\":{\"Column\":{\"Expression\":{\"SourceRef\":{\"Source\":\"a\"}},\"Property\":\"Date\"}},\"Function\":3}}}],\"Top\":1}}},\"Type\":2},{\"Name\":\"a\",\"Entity\":\"Ações\",\"Type\":0}],\"Where\":[{\"Condition\":{\"In\":{\"Expressions\":[{\"Column\":{\"Expression\":{\"SourceRef\":{\"Source\":\"a\"}},\"Property\":\"Date\"}}],\"Table\":{\"SourceRef\":{\"Source\":\"subquery\"}}}}}]},\"type\":\"TopN\",\"howCreated\":1}]",
          "height": 103.00,
          "width": 239.00,
          "x": 0.00,
          "y": 232.00,
          "z": 2000.00
        },
        {
          "config": "{\"name\":\"e5c515108e77c4615840\",\"layouts\":[{\"id\":0,\"position\":{\"x\":264,\"y\":190,\"z\":5000,\"width\":972,\"height\":453,\"tabOrder\":5000}}],\"singleVisual\":{\"visualType\":\"areaChart\",\"projections\":{\"Y\":[{\"queryRef\":\"Sum(Ações.Close)\"}],\"Category\":[{\"queryRef\":\"Ações.Date\",\"active\":true}]},\"prototypeQuery\":{\"Version\":2,\"From\":[{\"Name\":\"a\",\"Entity\":\"Ações\",\"Type\":0}],\"Select\":[{\"Aggregation\":{\"Expression\":{\"Column\":{\"Expression\":{\"SourceRef\":{\"Source\":\"a\"}},\"Property\":\"Close\"}},\"Function\":0},\"Name\":\"Sum(Ações.Close)\",\"NativeReferenceName\":\"Soma de Close\"},{\"Column\":{\"Expression\":{\"SourceRef\":{\"Source\":\"a\"}},\"Property\":\"Date\"},\"Name\":\"Ações.Date\",\"NativeReferenceName\":\"Date\"}],\"OrderBy\":[{\"Direction\":1,\"Expression\":{\"Column\":{\"Expression\":{\"SourceRef\":{\"Source\":\"a\"}},\"Property\":\"Date\"}}}]},\"drillFilterOtherVisuals\":true,\"hasDefaultSort\":true,\"objects\":{\"categoryAxis\":[{\"properties\":{\"labelColor\":{\"solid\":{\"color\":{\"expr\":{\"ThemeDataColor\":{\"ColorId\":0,\"Percent\":0}}}}},\"showAxisTitle\":{\"expr\":{\"Literal\":{\"Value\":\"false\"}}},\"axisType\":{\"expr\":{\"Literal\":{\"Value\":\"'Scalar'\"}}},\"show\":{\"expr\":{\"Literal\":{\"Value\":\"true\"}}},\"gridlineShow\":{\"expr\":{\"Literal\":{\"Value\":\"false\"}}}}}],\"valueAxis\":[{\"properties\":{\"labelColor\":{\"solid\":{\"color\":{\"expr\":{\"ThemeDataColor\":{\"ColorId\":0,\"Percent\":0}}}}},\"showAxisTitle\":{\"expr\":{\"Literal\":{\"Value\":\"false\"}}},\"gridlineShow\":{\"expr\":{\"Literal\":{\"Value\":\"false\"}}}}}],\"y2Axis\":[{\"properties\":{\"show\":{\"expr\":{\"Literal\":{\"Value\":\"true\"}}}}}],\"lineStyles\":[{\"properties\":{\"areaShow\":{\"expr\":{\"Literal\":{\"Value\":\"true\"}}},\"showMarker\":{\"expr\":{\"Literal\":{\"Value\":\"false\"}}},\"lineStyle\":{\"expr\":{\"Literal\":{\"Value\":\"'solid'\"}}},\"strokeLineJoin\":{\"expr\":{\"Literal\":{\"Value\":\"'round'\"}}},\"lineChartType\":{\"expr\":{\"Literal\":{\"Value\":\"'linear'\"}}},\"interpolationSmooth\":{\"expr\":{\"Literal\":{\"Value\":\"'cardinal'\"}}}}}],\"labels\":[{\"properties\":{\"show\":{\"expr\":{\"Literal\":{\"Value\":\"false\"}}}}}],\"seriesLabels\":[{\"properties\":{\"show\":{\"expr\":{\"Literal\":{\"Value\":\"false\"}}}}}],\"zoom\":[{\"properties\":{\"show\":{\"expr\":{\"Literal\":{\"Value\":\"true\"}}},\"showLabels\":{\"expr\":{\"Literal\":{\"Value\":\"false\"}}},\"showTooltip\":{\"expr\":{\"Literal\":{\"Value\":\"true\"}}}}}],\"dataPoint\":[{\"properties\":{\"fill\":{\"solid\":{\"color\":{\"expr\":{\"Literal\":{\"Value\":\"'#25B581'\"}}}}}},\"selector\":{\"metadata\":\"Sum(Ações.Close)\"}}]},\"vcObjects\":{\"background\":[{\"properties\":{\"show\":{\"expr\":{\"Literal\":{\"Value\":\"false\"}}}}}],\"title\":[{\"properties\":{\"fontColor\":{\"solid\":{\"color\":{\"expr\":{\"ThemeDataColor\":{\"ColorId\":0,\"Percent\":0}}}}},\"show\":{\"expr\":{\"Literal\":{\"Value\":\"false\"}}}}}],\"visualTooltip\":[{\"properties\":{\"show\":{\"expr\":{\"Literal\":{\"Value\":\"true\"}}},\"type\":{\"expr\":{\"Literal\":{\"Value\":\"'Canvas'\"}}},\"themedTitleFontColor\":{\"solid\":{\"color\":{\"expr\":{\"ThemeDataColor\":{\"ColorId\":1,\"Percent\":0}}}}},\"themedBackground\":{\"solid\":{\"color\":{\"expr\":{\"ThemeDataColor\":{\"ColorId\":0,\"Percent\":0}}}}},\"transparency\":{\"expr\":{\"Literal\":{\"Value\":\"15D\"}}}}}],\"visualHeader\":[{\"properties\":{\"show\":{\"expr\":{\"Literal\":{\"Value\":\"true\"}}}}}],\"dropShadow\":[{\"properties\":{\"show\":{\"expr\":{\"Literal\":{\"Value\":\"false\"}}}}}],\"border\":[{\"properties\":{\"show\":{\"expr\":{\"Literal\":{\"Value\":\"false\"}}}}}]}}}",
          "filters": "[]",
          "height": 453.00,
          "width": 972.00,
          "x": 264.00,
          "y": 190.00,
          "z": 5000.00
        },
        {
          "config": "{\"name\":\"f3c3939500be0266d0ed\",\"layouts\":[{\"id\":0,\"position\":{\"x\":667,\"y\":38,\"z\":0,\"width\":314,\"height\":42,\"tabOrder\":0}}],\"singleVisual\":{\"visualType\":\"slicer\",\"projections\":{\"Values\":[{\"queryRef\":\"Ações.ticker\",\"active\":true}]},\"prototypeQuery\":{\"Version\":2,\"From\":[{\"Name\":\"a\",\"Entity\":\"Ações\",\"Type\":0}],\"Select\":[{\"Column\":{\"Expression\":{\"SourceRef\":{\"Source\":\"a\"}},\"Property\":\"ticker\"},\"Name\":\"Ações.ticker\",\"NativeReferenceName\":\"ticker\"}]},\"drillFilterOtherVisuals\":true,\"objects\":{\"data\":[{\"properties\":{\"mode\":{\"expr\":{\"Literal\":{\"Value\":\"'Basic'\"}}}}}],\"pendingChangesIcon\":[{\"properties\":{\"show\":{\"expr\":{\"Literal\":{\"Value\":\"true\"}}}}}],\"general\":[{\"properties\":{\"orientation\":{\"expr\":{\"Literal\":{\"Value\":\"1D\"}}},\"filter\":{\"filter\":{\"Version\":2,\"From\":[{\"Name\":\"a\",\"Entity\":\"Ações\",\"Type\":0}],\"Where\":[{\"Condition\":{\"In\":{\"Expressions\":[{\"Column\":{\"Expression\":{\"SourceRef\":{\"Source\":\"a\"}},\"Property\":\"ticker\"}}],\"Values\":[[{\"Literal\":{\"Value\":\"'AMD'\"}}]]}}}]}}}}],\"selection\":[{\"properties\":{\"strictSingleSelect\":{\"expr\":{\"Literal\":{\"Value\":\"true\"}}}}}]},\"vcObjects\":{\"background\":[{\"properties\":{\"show\":{\"expr\":{\"Literal\":{\"Value\":\"false\"}}}}}]}}}",
          "filters": "[]",
          "height": 42.00,
          "width": 314.00,
          "x": 667.00,
          "y": 38.00,
          "z": 0.00
        }
      ],
      "width": 1280.00
    }
  ]
}